fast_trading_simulator/__init__.py
fast_trading_simulator/sim.py
fast_trading_simulator/utils.py
fast_trading_simulator-0.1.7.dist-info/METADATA
fast_trading_simulator-0.1.7.dist-info/WHEEL
fast_trading_simulator-0.1.7.dist-info/top_level.txt
fast_trading_simulator-0.1.7.dist-info/RECORD
