Metadata-Version: 2.4
Name: fast-trading-simulator
Version: 0.1.7
Summary: Numba accelerated minimalist trading simulator
Home-page: https://github.com/SerenaTradingResearch/fast-trading-simulator
Author: Ricky Ding
Author-email: e0134117@u.nus.edu
License: MIT
Keywords: trading,simulator,numba,quant,minimalist
Classifier: License :: OSI Approved :: MIT License
Classifier: Programming Language :: Python :: 3
Classifier: Topic :: Office/Business :: Financial
Requires-Python: >=3.8
Requires-Dist: numba
Requires-Dist: numpy
Requires-Dist: TA-Lib
Requires-Dist: matplotlib
Requires-Dist: pymoo
Requires-Dist: trading_models
Requires-Dist: crypto_data_downloader
Dynamic: author
Dynamic: author-email
Dynamic: classifier
Dynamic: description
Dynamic: description-content-type
Dynamic: home-page
Dynamic: keywords
Dynamic: license
Dynamic: requires-dist
Dynamic: requires-python
Dynamic: summary
